AUTHORS.rst
CONTRIBUTING.rst
HISTORY.rst
LICENSE
MANIFEST.in
README.rst
setup.cfg
setup.py
docs/Makefile
docs/authors.rst
docs/conf.py
docs/contributing.rst
docs/history.rst
docs/index.rst
docs/installation.rst
docs/make.bat
docs/readme.rst
docs/usage.rst
gcloud_datastore_odm/__init__.py
gcloud_datastore_odm/datastore_client.py
gcloud_datastore_odm/model.py
gcloud_datastore_odm/types.py
gcloud_datastore_odm.egg-info/PKG-INFO
gcloud_datastore_odm.egg-info/SOURCES.txt
gcloud_datastore_odm.egg-info/dependency_links.txt
gcloud_datastore_odm.egg-info/not-zip-safe
gcloud_datastore_odm.egg-info/requires.txt
gcloud_datastore_odm.egg-info/top_level.txt
tests/__init__.py
tests/test_gcloud_datastore_odm.py